CHANGES.rst
CONTRIBUTORS.rst
MANIFEST.in
README.rst
buildout.cfg
setup.py
travis.cfg
docs/LICENSE.GPL
docs/LICENSE.rst
src/ecreall/__init__.py
src/ecreall.handleexternaledition.egg-info/PKG-INFO
src/ecreall.handleexternaledition.egg-info/SOURCES.txt
src/ecreall.handleexternaledition.egg-info/dependency_links.txt
src/ecreall.handleexternaledition.egg-info/entry_points.txt
src/ecreall.handleexternaledition.egg-info/namespace_packages.txt
src/ecreall.handleexternaledition.egg-info/not-zip-safe
src/ecreall.handleexternaledition.egg-info/requires.txt
src/ecreall.handleexternaledition.egg-info/top_level.txt
src/ecreall/handleexternaledition/__init__.py
src/ecreall/handleexternaledition/configure.zcml
src/ecreall/handleexternaledition/handleedition.py
src/ecreall/handleexternaledition/interfaces.py
src/ecreall/handleexternaledition/setuphandlers.py
src/ecreall/handleexternaledition/testing.py
src/ecreall/handleexternaledition/testing.zcml
src/ecreall/handleexternaledition/locales/ecreall.handleexternaledition.pot
src/ecreall/handleexternaledition/locales/update.sh
src/ecreall/handleexternaledition/locales/fr/LC_MESSAGES/ecreall.handleexternaledition.po
src/ecreall/handleexternaledition/profiles/default/browserlayer.xml
src/ecreall/handleexternaledition/profiles/default/ecreallhandleexternaledition_marker.txt
src/ecreall/handleexternaledition/profiles/default/metadata.xml
src/ecreall/handleexternaledition/profiles/default/repositorytool.xml
src/ecreall/handleexternaledition/profiles/testing/metadata.xml
src/ecreall/handleexternaledition/tests/__init__.py
src/ecreall/handleexternaledition/tests/test_robot.py
src/ecreall/handleexternaledition/tests/test_setup.py
src/ecreall/handleexternaledition/tests/robot/.gitkeep