Metadata-Version: 1.1
Name: ecreall.handleexternaledition
Version: 0.2
Summary: Avoid documentviewer and history generation when we save during a zopeedit session
Home-page: http://pypi.python.org/pypi/ecreall.handleexternaledition
Author: Thomas Desvenain
Author-email: thomasdesvenain@ecreall.com
License: GPL
Keywords: zopeedit documentviewer cmfeditions
Platform: UNKNOWN
Classifier: Environment :: Web Environment
Classifier: Framework :: Plone
Classifier: Framework :: Plone :: 4.3
Classifier: Programming Language :: Python
Classifier: Programming Language :: Python :: 2.7
